[{"pk": 158, "model": "core.media", "fields": {"name": "Print Version", "title": 575, "url": "", "deleted": false, "date_updated": "2012-09-14T09:28:06.973", "date_created": "2012-09-14T09:28:06.973", "identifier": "1934516422"}}, {"pk": 159, "model": "core.media", "fields": {"name": "Print Version", "title": 583, "url": "", "deleted": false, "date_updated": "2012-09-14T09:28:06.973", "date_created": "2012-09-14T09:28:06.973", "identifier": "1456710591"}}, {"pk": 160, "model": "core.media", "fields": {"name": "Print Version", "title": 584, "url": "", "deleted": false, "date_updated": "2012-09-14T09:28:06.973", "date_created": "2012-09-14T09:28:06.973", "identifier": "1153756757"}}, {"pk": 161, "model": "core.media", "fields": {"name": "Print Version", "title": 589, "url": "", "deleted": false, "date_updated": "2012-09-14T09:28:06.973", "date_created": "2012-09-14T09:28:06.973", "identifier": "B004F9P8Z4"}}, {"pk": 162, "model": "core.media", "fields": {"name": "Print Version", "title": 598, "url": "", "deleted": false, "date_updated": "2012-09-14T09:28:06.973", "date_created": "2012-09-14T09:28:06.973", "identifier": "B004HILRJY"}}, {"pk": 163, "model": "core.media", "fields": {"name": "Print Version", "title": 603, "url": "", "deleted": false, "date_updated": "2012-09-14T09:28:06.973", "date_created": "2012-09-14T09:28:06.973", "identifier": "0973746750"}}, {"pk": 164, "model": "core.media", "fields": {"name": "Print Version", "title": 604, "url": "", "deleted": false, "date_updated": "2012-09-14T09:28:06.973", "date_created": "2012-09-14T09:28:06.973", "identifier": "1934516422"}}, {"pk": 165, "model": "core.media", "fields": {"name": "Print Version", "title": 606, "url": "", "deleted": false, "date_updated": "2012-09-14T09:28:06.973", "date_created": "2012-09-14T09:28:06.973", "identifier": "1453747583"}}, {"pk": 166, "model": "core.media", "fields": {"name": "Print Version", "title": 608, "url": "", "deleted": false, "date_updated": "2012-09-14T09:28:06.973", "date_created": "2012-09-14T09:28:06.973", "identifier": "1460968913"}}, {"pk": 167, "model": "core.media", "fields": {"name": "Print Version", "title": 609, "url": "", "deleted": false, "date_updated": "2012-09-14T09:28:06.973", "date_created": "2012-09-14T09:28:06.973", "identifier": "0615365426"}}, {"pk": 168, "model": "core.media", "fields": {"name": "Print Version", "title": 615, "url": "", "deleted": false, "date_updated": "2012-09-14T09:28:06.973", "date_created": "2012-09-14T09:28:06.973", "identifier": "B004K6MH4C"}}, {"pk": 169, "model": "core.media", "fields": {"name": "Print Version", "title": 619, "url": "", "deleted": false, "date_updated": "2012-09-14T09:28:06.973", "date_created": "2012-09-14T09:28:06.973", "identifier": "0979533112"}}, {"pk": 170, "model": "core.media", "fields": {"name": "Print Version", "title": 620, "url": "", "deleted": false, "date_updated": "2012-09-14T09:28:06.973", "date_created": "2012-09-14T09:28:06.973", "identifier": "0966668901"}}, {"pk": 171, "model": "core.media", "fields": {"name": "Print Version", "title": 622, "url": "", "deleted": false, "date_updated": "2012-09-14T09:28:06.973", "date_created": "2012-09-14T09:28:06.973", "identifier": "1614500118"}}, {"pk": 172, "model": "core.media", "fields": {"name": "Print Version", "title": 627, "url": "", "deleted": false, "date_updated": "2012-09-14T09:28:06.973", "date_created": "2012-09-14T09:28:06.973", "identifier": "1460968867"}}, {"pk": 173, "model": "core.media", "fields": {"name": "Print Version", "title": 628, "url": "", "deleted": false, "date_updated": "2012-09-14T09:28:06.973", "date_created": "2012-09-14T09:28:06.973", "identifier": "144042232X"}}, {"pk": 174, "model": "core.media", "fields": {"name": "Print Version", "title": 629, "url": "", "deleted": false, "date_updated": "2012-09-14T09:28:06.973", "date_created": "2012-09-14T09:28:06.973", "identifier": "1606437550"}}, {"pk": 175, "model": "core.media", "fields": {"name": "Print Version", "title": 630, "url": "", "deleted": false, "date_updated": "2012-09-14T09:28:06.973", "date_created": "2012-09-14T09:28:06.973", "identifier": "1934516422"}}, {"pk": 176, "model": "core.media", "fields": {"name": "Print Version", "title": 631, "url": "", "deleted": false, "date_updated": "2012-09-14T09:28:06.973", "date_created": "2012-09-14T09:28:06.973", "identifier": "0980865905"}}, {"pk": 177, "model": "core.media", "fields": {"name": "Print Version", "title": 634, "url": "", "deleted": false, "date_updated": "2012-09-14T09:28:06.973", "date_created": "2012-09-14T09:28:06.973", "identifier": "1439201609"}}, {"pk": 178, "model": "core.media", "fields": {"name": "Print Version", "title": 638, "url": "", "deleted": false, "date_updated": "2012-09-14T09:28:06.973", "date_created": "2012-09-14T09:28:06.973", "identifier": "1461037328"}}, {"pk": 179, "model": "core.media", "fields": {"name": "Print Version", "title": 641, "url": "", "deleted": false, "date_updated": "2012-09-14T09:28:06.973", "date_created": "2012-09-14T09:28:06.973", "identifier": "1461046289"}}, {"pk": 180, "model": "core.media", "fields": {"name": "Print Version", "title": 645, "url": "", "deleted": false, "date_updated": "2012-09-14T09:28:06.973", "date_created": "2012-09-14T09:28:06.973", "identifier": "B005BR2618"}}, {"pk": 181, "model": "core.media", "fields": {"name": "Print Version", "title": 648, "url": "", "deleted": false, "date_updated": "2012-09-14T09:28:06.973", "date_created": "2012-09-14T09:28:06.973", "identifier": "B0056IBONS"}}, {"pk": 182, "model": "core.media", "fields": {"name": "Print Version", "title": 650, "url": "", "deleted": false, "date_updated": "2012-09-14T09:28:06.973", "date_created": "2012-09-14T09:28:06.973", "identifier": "0977385116"}}, {"pk": 183, "model": "core.media", "fields": {"name": "Print Version", "title": 652, "url": "", "deleted": false, "date_updated": "2012-09-14T09:28:06.973", "date_created": "2012-09-14T09:28:06.973", "identifier": "B00570S7RQ"}}, {"pk": 184, "model": "core.media", "fields": {"name": "Print Version", "title": 654, "url": "", "deleted": false, "date_updated": "2012-09-14T09:28:06.973", "date_created": "2012-09-14T09:28:06.973", "identifier": "B004UJ35B8"}}, {"pk": 185, "model": "core.media", "fields": {"name": "Print Version", "title": 655, "url": "", "deleted": false, "date_updated": "2012-09-14T09:28:06.973", "date_created": "2012-09-14T09:28:06.973", "identifier": "1463599072"}}, {"pk": 186, "model": "core.media", "fields": {"name": "Print Version", "title": 656, "url": "", "deleted": false, "date_updated": "2012-09-14T09:28:06.973", "date_created": "2012-09-14T09:28:06.973", "identifier": "B008DM1MP4"}}, {"pk": 187, "model": "core.media", "fields": {"name": "Print Version", "title": 657, "url": "", "deleted": false, "date_updated": "2012-09-14T09:28:06.973", "date_created": "2012-09-14T09:28:06.973", "identifier": "1935670751"}}, {"pk": 188, "model": "core.media", "fields": {"name": "Print Version", "title": 661, "url": "", "deleted": false, "date_updated": "2012-09-14T09:28:06.973", "date_created": "2012-09-14T09:28:06.973", "identifier": "1453760318"}}, {"pk": 189, "model": "core.media", "fields": {"name": "Print Version", "title": 666, "url": "", "deleted": false, "date_updated": "2012-09-14T09:28:06.973", "date_created": "2012-09-14T09:28:06.973", "identifier": "B004K1F0E6"}}, {"pk": 190, "model": "core.media", "fields": {"name": "Print Version", "title": 668, "url": "", "deleted": false, "date_updated": "2012-09-14T09:28:06.973", "date_created": "2012-09-14T09:28:06.973", "identifier": "B001TB1WJM"}}, {"pk": 191, "model": "core.media", "fields": {"name": "Print Version", "title": 669, "url": "", "deleted": false, "date_updated": "2012-09-14T09:28:06.973", "date_created": "2012-09-14T09:28:06.973", "identifier": "0615319149"}}, {"pk": 192, "model": "core.media", "fields": {"name": "Print Version", "title": 673, "url": "", "deleted": false, "date_updated": "2012-09-14T09:28:06.973", "date_created": "2012-09-14T09:28:06.973", "identifier": "1608138062"}}, {"pk": 193, "model": "core.media", "fields": {"name": "Print Version", "title": 678, "url": "", "deleted": false, "date_updated": "2012-09-14T09:28:06.973", "date_created": "2012-09-14T09:28:06.973", "identifier": "B003TFESMO"}}, {"pk": 194, "model": "core.media", "fields": {"name": "Print Version", "title": 683, "url": "", "deleted": false, "date_updated": "2012-09-14T09:28:06.973", "date_created": "2012-09-14T09:28:06.973", "identifier": "097622352X"}}, {"pk": 195, "model": "core.media", "fields": {"name": "Print Version", "title": 687, "url": "", "deleted": false, "date_updated": "2012-09-14T09:28:06.973", "date_created": "2012-09-14T09:28:06.973", "identifier": "0983292507"}}, {"pk": 196, "model": "core.media", "fields": {"name": "Print Version", "title": 690, "url": "", "deleted": false, "date_updated": "2012-09-14T09:28:06.973", "date_created": "2012-09-14T09:28:06.973", "identifier": "B005DBOUSE"}}, {"pk": 197, "model": "core.media", "fields": {"name": "Print Version", "title": 691, "url": "", "deleted": false, "date_updated": "2012-09-14T09:28:06.973", "date_created": "2012-09-14T09:28:06.973", "identifier": "B00558UVOW"}}, {"pk": 198, "model": "core.media", "fields": {"name": "Print Version", "title": 692, "url": "", "deleted": false, "date_updated": "2012-09-14T09:28:06.973", "date_created": "2012-09-14T09:28:06.973", "identifier": "B004NIFNKM"}}, {"pk": 199, "model": "core.media", "fields": {"name": "Print Version", "title": 693, "url": "", "deleted": false, "date_updated": "2012-09-14T09:28:06.973", "date_created": "2012-09-14T09:28:06.973", "identifier": "1466251654"}}, {"pk": 200, "model": "core.media", "fields": {"name": "Print Version", "title": 697, "url": "", "deleted": false, "date_updated": "2012-09-14T09:28:06.973", "date_created": "2012-09-14T09:28:06.973", "identifier": "1447771850"}}, {"pk": 201, "model": "core.media", "fields": {"name": "Print Version", "title": 700, "url": "", "deleted": false, "date_updated": "2012-09-14T09:28:06.973", "date_created": "2012-09-14T09:28:06.973", "identifier": "0983196338"}}, {"pk": 202, "model": "core.media", "fields": {"name": "Print Version", "title": 702, "url": "", "deleted": false, "date_updated": "2012-09-14T09:28:06.973", "date_created": "2012-09-14T09:28:06.973", "identifier": "B005U3UYOY"}}, {"pk": 203, "model": "core.media", "fields": {"name": "Print Version", "title": 704, "url": "", "deleted": false, "date_updated": "2012-09-14T09:28:06.973", "date_created": "2012-09-14T09:28:06.973", "identifier": "B006H3C4ZI"}}, {"pk": 204, "model": "core.media", "fields": {"name": "Print Version", "title": 705, "url": "", "deleted": false, "date_updated": "2012-09-14T09:28:06.973", "date_created": "2012-09-14T09:28:06.973", "identifier": "0982765185"}}, {"pk": 205, "model": "core.media", "fields": {"name": "Print Version", "title": 706, "url": "", "deleted": false, "date_updated": "2012-09-14T09:28:06.973", "date_created": "2012-09-14T09:28:06.973", "identifier": "B005LSCXRY"}}, {"pk": 206, "model": "core.media", "fields": {"name": "Print Version", "title": 708, "url": "", "deleted": false, "date_updated": "2012-09-14T09:28:06.973", "date_created": "2012-09-14T09:28:06.973", "identifier": "B005ZHTMX4"}}, {"pk": 207, "model": "core.media", "fields": {"name": "Print Version", "title": 709, "url": "", "deleted": false, "date_updated": "2012-09-14T09:28:06.973", "date_created": "2012-09-14T09:28:06.973", "identifier": "B0067Y3K9Q"}}, {"pk": 208, "model": "core.media", "fields": {"name": "Print Version", "title": 717, "url": "", "deleted": false, "date_updated": "2012-09-14T09:28:06.973", "date_created": "2012-09-14T09:28:06.973", "identifier": "1467984515"}}, {"pk": 209, "model": "core.media", "fields": {"name": "Print Version", "title": 720, "url": "", "deleted": false, "date_updated": "2012-09-14T09:28:06.973", "date_created": "2012-09-14T09:28:06.973", "identifier": "1463627548"}}, {"pk": 211, "model": "core.media", "fields": {"name": "Print Version", "title": 723, "url": "", "deleted": false, "date_updated": "2012-09-14T09:28:06.973", "date_created": "2012-09-14T09:28:06.973", "identifier": "1466280956"}}, {"pk": 212, "model": "core.media", "fields": {"name": "Print Version", "title": 730, "url": "", "deleted": false, "date_updated": "2012-09-14T09:28:06.973", "date_created": "2012-09-14T09:28:06.973", "identifier": "0973746777"}}, {"pk": 213, "model": "core.media", "fields": {"name": "Print Version", "title": 731, "url": "", "deleted": false, "date_updated": "2012-09-14T09:28:06.973", "date_created": "2012-09-14T09:28:06.973", "identifier": "B001R4C6XM"}}, {"pk": 214, "model": "core.media", "fields": {"name": "Print Version", "title": 732, "url": "", "deleted": false, "date_updated": "2012-09-14T09:28:06.973", "date_created": "2012-09-14T09:28:06.973", "identifier": "B007SA6JW8"}}, {"pk": 215, "model": "core.media", "fields": {"name": "Print Version", "title": 733, "url": "", "deleted": false, "date_updated": "2012-09-14T09:28:06.973", "date_created": "2012-09-14T09:28:06.973", "identifier": "B00361FAXW"}}, {"pk": 216, "model": "core.media", "fields": {"name": "Print Version", "title": 737, "url": "", "deleted": false, "date_updated": "2012-09-14T09:28:06.973", "date_created": "2012-09-14T09:28:06.973", "identifier": "B007GNCE8K"}}, {"pk": 217, "model": "core.media", "fields": {"name": "Print Version", "title": 738, "url": "", "deleted": false, "date_updated": "2012-09-14T09:28:06.973", "date_created": "2012-09-14T09:28:06.973", "identifier": "B008CLWIG8"}}, {"pk": 218, "model": "core.media", "fields": {"name": "Print Version", "title": 739, "url": "", "deleted": false, "date_updated": "2012-09-14T09:28:06.973", "date_created": "2012-09-14T09:28:06.973", "identifier": "B007LS7MIM"}}, {"pk": 219, "model": "core.media", "fields": {"name": "Print Version", "title": 740, "url": "", "deleted": false, "date_updated": "2012-09-14T09:28:06.973", "date_created": "2012-09-14T09:28:06.973", "identifier": "B0078X2PJ6"}}, {"pk": 220, "model": "core.media", "fields": {"name": "Print Version", "title": 742, "url": "", "deleted": false, "date_updated": "2012-09-14T09:28:06.973", "date_created": "2012-09-14T09:28:06.973", "identifier": "1475166966"}}, {"pk": 221, "model": "core.media", "fields": {"name": "Print Version", "title": 744, "url": "", "deleted": false, "date_updated": "2012-09-14T09:28:06.973", "date_created": "2012-09-14T09:28:06.973", "identifier": "B007F1TUWQ"}}, {"pk": 222, "model": "core.media", "fields": {"name": "Print Version", "title": 746, "url": "", "deleted": false, "date_updated": "2012-09-14T09:28:06.973", "date_created": "2012-09-14T09:28:06.973", "identifier": "1478242213"}}, {"pk": 223, "model": "core.media", "fields": {"name": "Print Version", "title": 747, "url": "", "deleted": false, "date_updated": "2012-09-14T09:28:06.973", "date_created": "2012-09-14T09:28:06.973", "identifier": "B005YN675A"}}, {"pk": 224, "model": "core.media", "fields": {"name": "Print Version", "title": 748, "url": "", "deleted": false, "date_updated": "2012-09-14T09:28:06.973", "date_created": "2012-09-14T09:28:06.973", "identifier": "B008VL8UAC"}}, {"pk": 225, "model": "core.media", "fields": {"name": "Print Version", "title": 749, "url": "", "deleted": false, "date_updated": "2012-09-14T09:28:06.973", "date_created": "2012-09-14T09:28:06.973", "identifier": "B004BA57W6"}}, {"pk": 227, "model": "core.media", "fields": {"name": "Print Version", "title": 751, "url": "", "deleted": false, "date_updated": "2012-09-14T09:28:06.973", "date_created": "2012-09-14T09:28:06.973", "identifier": "B008KA454E"}}, {"pk": 228, "model": "core.media", "fields": {"name": "Print Version", "title": 752, "url": "", "deleted": false, "date_updated": "2012-09-14T09:28:06.973", "date_created": "2012-09-14T09:28:06.973", "identifier": "B0086XSYR4"}}, {"pk": 229, "model": "core.media", "fields": {"name": "Print Version", "title": 753, "url": "", "deleted": false, "date_updated": "2012-09-16T17:44:32", "date_created": "2012-09-16T17:44:32", "identifier": "B007W6RDBY"}}, {"pk": 230, "model": "core.media", "fields": {"name": "Print Version", "title": 674, "url": "", "deleted": false, "date_updated": "2012-09-17T14:49:50.210", "date_created": "2012-09-17T14:49:50.210", "identifier": "B004H1TDB0"}}, {"pk": 231, "model": "core.media", "fields": {"name": "Print Version", "title": 86, "url": "", "deleted": false, "date_updated": "2012-09-18T22:38:22.063", "date_created": "2012-09-18T22:38:22.063", "identifier": "1411684923"}}, {"pk": 238, "model": "core.media", "fields": {"name": "Print Version", "title": 644, "url": "", "deleted": false, "date_updated": "2012-09-22T07:28:25.848", "date_created": "2012-09-22T07:28:25.848", "identifier": "B005GIBF7I"}}, {"pk": 226, "model": "core.media", "fields": {"name": "Print Version", "title": 749, "url": "", "deleted": false, "date_updated": "2012-09-22T16:10:19.863", "date_created": "2012-09-14T09:28:06.973", "identifier": "B005GIH70M"}}, {"pk": 241, "model": "core.media", "fields": {"name": "Print Version", "title": 45, "url": "", "deleted": false, "date_updated": "2012-09-22T16:47:16.475", "date_created": "2012-09-22T16:47:16.475", "identifier": "B004JZXBQC"}}, {"pk": 244, "model": "core.media", "fields": {"name": "Print Version", "title": 104, "url": "", "deleted": false, "date_updated": "2012-09-22T18:09:22.019", "date_created": "2012-09-22T18:09:22.019", "identifier": "B003XRE6BQ"}}, {"pk": 247, "model": "core.media", "fields": {"name": "Print Version", "title": 105, "url": "", "deleted": false, "date_updated": "2012-09-22T18:26:31.152", "date_created": "2012-09-22T18:26:31.152", "identifier": "1412089417"}}, {"pk": 249, "model": "core.media", "fields": {"name": "Print Version", "title": 191, "url": "", "deleted": false, "date_updated": "2012-09-22T18:34:40.498", "date_created": "2012-09-22T18:34:40.498", "identifier": "1897217579"}}, {"pk": 251, "model": "core.media", "fields": {"name": "Print Version", "title": 328, "url": "", "deleted": false, "date_updated": "2012-09-23T17:16:21.584", "date_created": "2012-09-23T17:16:21.584", "identifier": "B0029XGNJ8"}}, {"pk": 253, "model": "core.media", "fields": {"name": "Print Version", "title": 141, "url": "", "deleted": false, "date_updated": "2012-09-23T17:36:43.614", "date_created": "2012-09-23T17:36:43.614", "identifier": "B0029F1WAQ"}}, {"pk": 255, "model": "core.media", "fields": {"name": "Print Version", "title": 91, "url": "", "deleted": false, "date_updated": "2012-09-23T17:45:00.888", "date_created": "2012-09-23T17:45:00.887", "identifier": "1411682866"}}, {"pk": 257, "model": "core.media", "fields": {"name": "Print Version", "title": 246, "url": "", "deleted": false, "date_updated": "2012-09-23T17:55:06.452", "date_created": "2012-09-23T17:55:06.452", "identifier": "B003YRIIHS"}}, {"pk": 259, "model": "core.media", "fields": {"name": "Print Version", "title": 498, "url": "", "deleted": false, "date_updated": "2012-09-23T18:38:49.153", "date_created": "2012-09-23T18:38:49.153", "identifier": "B003MAK5ZA"}}, {"pk": 261, "model": "core.media", "fields": {"name": "Print Version", "title": 494, "url": "", "deleted": false, "date_updated": "2012-09-23T18:45:12.432", "date_created": "2012-09-23T18:45:12.432", "identifier": "B001HEIDZM"}}, {"pk": 263, "model": "core.media", "fields": {"name": "Print Version", "title": 99, "url": "", "deleted": false, "date_updated": "2012-09-23T18:57:33.159", "date_created": "2012-09-23T18:57:33.159", "identifier": "0761828389"}}, {"pk": 265, "model": "core.media", "fields": {"name": "Print Version", "title": 550, "url": "", "deleted": false, "date_updated": "2012-09-23T19:09:44.255", "date_created": "2012-09-23T19:09:44.255", "identifier": "B006MGTR0A"}}, {"pk": 267, "model": "core.media", "fields": {"name": "Print Version", "title": 442, "url": "", "deleted": false, "date_updated": "2012-09-23T19:57:16.058", "date_created": "2012-09-23T19:57:16.058", "identifier": "B0058KTLG6"}}, {"pk": 269, "model": "core.media", "fields": {"name": "Print Version", "title": 343, "url": "", "deleted": false, "date_updated": "2012-09-23T20:03:42.971", "date_created": "2012-09-23T20:03:42.971", "identifier": "1594147795"}}, {"pk": 235, "model": "core.media", "fields": {"name": "Print Version", "title": 256, "url": "", "deleted": false, "date_updated": "2012-09-21T11:45:27.947", "date_created": "2012-09-21T11:45:27.947", "identifier": "B0065EC27E"}}, {"pk": 233, "model": "core.media", "fields": {"name": "Print Version", "title": 100, "url": "", "deleted": false, "date_updated": "2012-09-21T11:24:30.501", "date_created": "2012-09-21T11:24:30.501", "identifier": "B0027MJU0A"}}, {"pk": 236, "model": "core.media", "fields": {"name": "Print Version", "title": 157, "url": "", "deleted": false, "date_updated": "2012-09-21T11:47:33.544", "date_created": "2012-09-21T11:47:33.543", "identifier": "B005S67GPS"}}, {"pk": 239, "model": "core.media", "fields": {"name": "Print Version", "title": 425, "url": "", "deleted": false, "date_updated": "2012-09-22T16:24:06.868", "date_created": "2012-09-22T16:24:06.868", "identifier": "B0029ZEW4O"}}, {"pk": 242, "model": "core.media", "fields": {"name": "Print Version", "title": 292, "url": "", "deleted": false, "date_updated": "2012-09-22T18:05:03.121", "date_created": "2012-09-22T18:05:03.121", "identifier": "0646484443"}}, {"pk": 245, "model": "core.media", "fields": {"name": "Print Version", "title": 696, "url": "", "deleted": false, "date_updated": "2012-09-22T18:11:21.692", "date_created": "2012-09-22T18:11:21.692", "identifier": "B005C20E5C"}}, {"pk": 248, "model": "core.media", "fields": {"name": "Print Version", "title": 303, "url": "", "deleted": false, "date_updated": "2012-09-22T18:30:09.799", "date_created": "2012-09-22T18:30:09.799", "identifier": "141402682X"}}, {"pk": 250, "model": "core.media", "fields": {"name": "Print Version", "title": 420, "url": "", "deleted": false, "date_updated": "2012-09-22T18:49:44.765", "date_created": "2012-09-22T18:49:44.765", "identifier": "B003KN3ZU6"}}, {"pk": 252, "model": "core.media", "fields": {"name": "Print Version", "title": 401, "url": "", "deleted": false, "date_updated": "2012-09-23T17:17:45.988", "date_created": "2012-09-23T17:17:45.988", "identifier": "B0029U15CG"}}, {"pk": 254, "model": "core.media", "fields": {"name": "Print Version", "title": 721, "url": "", "deleted": false, "date_updated": "2012-09-23T17:43:03.482", "date_created": "2012-09-23T17:43:03.482", "identifier": "B005KG3NU8"}}, {"pk": 256, "model": "core.media", "fields": {"name": "Print Version", "title": 529, "url": "", "deleted": false, "date_updated": "2012-09-23T17:46:51.700", "date_created": "2012-09-23T17:46:51.700", "identifier": "B00628B2EC"}}, {"pk": 258, "model": "core.media", "fields": {"name": "Print Version", "title": 580, "url": "", "deleted": false, "date_updated": "2012-09-23T18:35:05.326", "date_created": "2012-09-23T18:35:05.326", "identifier": "B0048EK1GW"}}, {"pk": 260, "model": "core.media", "fields": {"name": "Print Version", "title": 114, "url": "", "deleted": false, "date_updated": "2012-09-23T18:43:44.226", "date_created": "2012-09-23T18:43:44.226", "identifier": "B000JMKX4W"}}, {"pk": 262, "model": "core.media", "fields": {"name": "Print Version", "title": 121, "url": "", "deleted": false, "date_updated": "2012-09-23T18:52:19.693", "date_created": "2012-09-23T18:52:19.693", "identifier": "0761828389"}}, {"pk": 264, "model": "core.media", "fields": {"name": "Print Version", "title": 111, "url": "", "deleted": false, "date_updated": "2012-09-23T18:59:34.943", "date_created": "2012-09-23T18:59:34.943", "identifier": "B002JVWS9O"}}, {"pk": 266, "model": "core.media", "fields": {"name": "Print Version", "title": 242, "url": "", "deleted": false, "date_updated": "2012-09-23T19:20:33.510", "date_created": "2012-09-23T19:20:33.510", "identifier": "0615603459"}}, {"pk": 268, "model": "core.media", "fields": {"name": "Print Version", "title": 408, "url": "", "deleted": false, "date_updated": "2012-09-23T20:00:39.392", "date_created": "2012-09-23T20:00:39.392", "identifier": "B002QHVW1G"}}, {"pk": 270, "model": "core.media", "fields": {"name": "Print Version", "title": 671, "url": "", "deleted": false, "date_updated": "2012-09-23T20:06:14.121", "date_created": "2012-09-23T20:06:14.121", "identifier": "B0082D2EWE"}}, {"pk": 153, "model": "core.media", "fields": {"name": "Print Version", "title": 562, "url": "", "deleted": false, "date_updated": "2012-09-14T09:28:06.973", "date_created": "2012-09-14T09:28:06.973", "identifier": "B0044XV0R6"}}, {"pk": 154, "model": "core.media", "fields": {"name": "Print Version", "title": 563, "url": "", "deleted": false, "date_updated": "2012-09-14T09:28:06.973", "date_created": "2012-09-14T09:28:06.973", "identifier": "1453829369"}}, {"pk": 155, "model": "core.media", "fields": {"name": "Print Version", "title": 566, "url": "", "deleted": false, "date_updated": "2012-09-14T09:28:06.973", "date_created": "2012-09-14T09:28:06.973", "identifier": "1896944884"}}, {"pk": 156, "model": "core.media", "fields": {"name": "Print Version", "title": 572, "url": "", "deleted": false, "date_updated": "2012-09-14T09:28:06.973", "date_created": "2012-09-14T09:28:06.973", "identifier": "B004EEPMTW"}}, {"pk": 157, "model": "core.media", "fields": {"name": "Print Version", "title": 573, "url": "", "deleted": false, "date_updated": "2012-09-14T09:28:06.973", "date_created": "2012-09-14T09:28:06.973", "identifier": "B004H1T9QE"}}, {"pk": 234, "model": "core.media", "fields": {"name": "Print Version", "title": 132, "url": "", "deleted": false, "date_updated": "2012-09-21T11:30:15.544", "date_created": "2012-09-21T11:30:15.544", "identifier": "B002ZVPSOU"}}, {"pk": 237, "model": "core.media", "fields": {"name": "Print Version", "title": 308, "url": "", "deleted": false, "date_updated": "2012-09-21T11:50:19.211", "date_created": "2012-09-21T11:50:19.211", "identifier": "B004A90DAY"}}, {"pk": 240, "model": "core.media", "fields": {"name": "Print Version", "title": 59, "url": "", "deleted": false, "date_updated": "2012-09-22T16:29:12.192", "date_created": "2012-09-22T16:29:12.192", "identifier": "B0029ZEW4O"}}, {"pk": 243, "model": "core.media", "fields": {"name": "Print Version", "title": 611, "url": "", "deleted": false, "date_updated": "2012-09-22T18:07:58.810", "date_created": "2012-09-22T18:07:58.810", "identifier": "B004SI41GY"}}, {"pk": 246, "model": "core.media", "fields": {"name": "Print Version", "title": 265, "url": "", "deleted": false, "date_updated": "2012-09-22T18:17:39.746", "date_created": "2012-09-22T18:17:39.746", "identifier": "B004TRQBIA"}}, {"pk": 117, "model": "core.media", "fields": {"name": "Smashwords Version", "title": 655, "url": "", "deleted": false, "date_updated": "2012-09-19T23:59:26.159", "date_created": "2012-09-19T23:59:26.159", "identifier": "48558"}}, {"pk": 118, "model": "core.media", "fields": {"name": "Smashwords Version", "title": 661, "url": "", "deleted": false, "date_updated": "2012-09-19T23:59:26.159", "date_created": "2012-09-19T23:59:26.159", "identifier": "22878"}}, {"pk": 119, "model": "core.media", "fields": {"name": "Smashwords Version", "title": 664, "url": "", "deleted": false, "date_updated": "2012-09-19T23:59:26.159", "date_created": "2012-09-19T23:59:26.159", "identifier": "44948"}}, {"pk": 120, "model": "core.media", "fields": {"name": "Smashwords Version", "title": 644, "url": "", "deleted": false, "date_updated": "2012-09-19T23:59:26.159", "date_created": "2012-09-19T23:59:26.159", "identifier": "80012"}}, {"pk": 121, "model": "core.media", "fields": {"name": "Smashwords Version", "title": 669, "url": "", "deleted": false, "date_updated": "2012-09-19T23:59:26.159", "date_created": "2012-09-19T23:59:26.159", "identifier": "7770"}}, {"pk": 122, "model": "core.media", "fields": {"name": "Smashwords Version", "title": 674, "url": "", "deleted": false, "date_updated": "2012-09-19T23:59:26.159", "date_created": "2012-09-19T23:59:26.159", "identifier": "31003"}}, {"pk": 123, "model": "core.media", "fields": {"name": "Smashwords Version", "title": 546, "url": "", "deleted": false, "date_updated": "2012-09-19T23:59:26.159", "date_created": "2012-09-19T23:59:26.159", "identifier": "24009"}}, {"pk": 232, "model": "core.media", "fields": {"name": "Smashwords Version", "title": 627, "url": "", "deleted": false, "date_updated": "2012-09-20T00:05:19.288", "date_created": "2012-09-20T00:05:19.288", "identifier": "44725"}}, {"pk": 125, "model": "core.media", "fields": {"name": "Smashwords Version", "title": 678, "url": "", "deleted": false, "date_updated": "2012-09-19T23:59:26.159", "date_created": "2012-09-19T23:59:26.159", "identifier": "13613"}}, {"pk": 126, "model": "core.media", "fields": {"name": "Smashwords Version", "title": 220, "url": "", "deleted": false, "date_updated": "2012-09-19T23:59:26.159", "date_created": "2012-09-19T23:59:26.159", "identifier": "50048"}}, {"pk": 127, "model": "core.media", "fields": {"name": "Smashwords Version", "title": 589, "url": "", "deleted": false, "date_updated": "2012-09-19T23:59:26.159", "date_created": "2012-09-19T23:59:26.159", "identifier": "32292"}}, {"pk": 128, "model": "core.media", "fields": {"name": "Smashwords Version", "title": 683, "url": "", "deleted": false, "date_updated": "2012-09-19T23:59:26.159", "date_created": "2012-09-19T23:59:26.159", "identifier": "939"}}, {"pk": 129, "model": "core.media", "fields": {"name": "Smashwords Version", "title": 688, "url": "", "deleted": false, "date_updated": "2012-09-19T23:59:26.159", "date_created": "2012-09-19T23:59:26.159", "identifier": "23521"}}, {"pk": 130, "model": "core.media", "fields": {"name": "Smashwords Version", "title": 691, "url": "", "deleted": false, "date_updated": "2012-09-19T23:59:26.159", "date_created": "2012-09-19T23:59:26.159", "identifier": "61283"}}, {"pk": 131, "model": "core.media", "fields": {"name": "Smashwords Version", "title": 693, "url": "", "deleted": false, "date_updated": "2012-09-19T23:59:26.159", "date_created": "2012-09-19T23:59:26.159", "identifier": "82830"}}, {"pk": 132, "model": "core.media", "fields": {"name": "Smashwords Version", "title": 657, "url": "", "deleted": false, "date_updated": "2012-09-19T23:59:26.159", "date_created": "2012-09-19T23:59:26.159", "identifier": "66292"}}, {"pk": 133, "model": "core.media", "fields": {"name": "Smashwords Version", "title": 687, "url": "", "deleted": false, "date_updated": "2012-09-19T23:59:26.159", "date_created": "2012-09-19T23:59:26.159", "identifier": "50729"}}, {"pk": 134, "model": "core.media", "fields": {"name": "Smashwords Version", "title": 697, "url": "", "deleted": false, "date_updated": "2012-09-19T23:59:26.159", "date_created": "2012-09-19T23:59:26.159", "identifier": "87964"}}, {"pk": 135, "model": "core.media", "fields": {"name": "Smashwords Version", "title": 448, "url": "", "deleted": false, "date_updated": "2012-09-19T23:59:26.159", "date_created": "2012-09-19T23:59:26.159", "identifier": "102533"}}, {"pk": 136, "model": "core.media", "fields": {"name": "Smashwords Version", "title": 117, "url": "", "deleted": false, "date_updated": "2012-09-19T23:59:26.159", "date_created": "2012-09-19T23:59:26.159", "identifier": "35254"}}, {"pk": 137, "model": "core.media", "fields": {"name": "Smashwords Version", "title": 702, "url": "", "deleted": false, "date_updated": "2012-09-19T23:59:26.159", "date_created": "2012-09-19T23:59:26.159", "identifier": "104626"}}, {"pk": 138, "model": "core.media", "fields": {"name": "Smashwords Version", "title": 658, "url": "", "deleted": false, "date_updated": "2012-09-19T23:59:26.159", "date_created": "2012-09-19T23:59:26.159", "identifier": "104653"}}, {"pk": 139, "model": "core.media", "fields": {"name": "Smashwords Version", "title": 690, "url": "", "deleted": false, "date_updated": "2012-09-19T23:59:26.159", "date_created": "2012-09-19T23:59:26.159", "identifier": "73832"}}, {"pk": 140, "model": "core.media", "fields": {"name": "Smashwords Version", "title": 705, "url": "", "deleted": false, "date_updated": "2012-09-19T23:59:26.159", "date_created": "2012-09-19T23:59:26.159", "identifier": "63262"}}, {"pk": 141, "model": "core.media", "fields": {"name": "Smashwords Version", "title": 632, "url": "", "deleted": false, "date_updated": "2012-09-19T23:59:26.159", "date_created": "2012-09-19T23:59:26.159", "identifier": "108245"}}, {"pk": 142, "model": "core.media", "fields": {"name": "Smashwords Version", "title": 719, "url": "", "deleted": false, "date_updated": "2012-09-19T23:59:26.159", "date_created": "2012-09-19T23:59:26.159", "identifier": "127672"}}, {"pk": 143, "model": "core.media", "fields": {"name": "Smashwords Version", "title": 339, "url": "", "deleted": false, "date_updated": "2012-09-19T23:59:26.159", "date_created": "2012-09-19T23:59:26.159", "identifier": "131807"}}, {"pk": 144, "model": "core.media", "fields": {"name": "Smashwords Version", "title": 392, "url": "", "deleted": false, "date_updated": "2012-09-19T23:59:26.159", "date_created": "2012-09-19T23:59:26.159", "identifier": "108602"}}, {"pk": 145, "model": "core.media", "fields": {"name": "Smashwords Version", "title": 725, "url": "", "deleted": false, "date_updated": "2012-09-19T23:59:26.159", "date_created": "2012-09-19T23:59:26.159", "identifier": "108641"}}, {"pk": 146, "model": "core.media", "fields": {"name": "Smashwords Version", "title": 726, "url": "", "deleted": false, "date_updated": "2012-09-19T23:59:26.159", "date_created": "2012-09-19T23:59:26.159", "identifier": "96923"}}, {"pk": 147, "model": "core.media", "fields": {"name": "Smashwords Version", "title": 730, "url": "", "deleted": false, "date_updated": "2012-09-19T23:59:26.159", "date_created": "2012-09-19T23:59:26.159", "identifier": "133220"}}, {"pk": 148, "model": "core.media", "fields": {"name": "Smashwords Version", "title": 733, "url": "", "deleted": false, "date_updated": "2012-09-19T23:59:26.159", "date_created": "2012-09-19T23:59:26.159", "identifier": "18029"}}, {"pk": 149, "model": "core.media", "fields": {"name": "Smashwords Version", "title": 737, "url": "", "deleted": false, "date_updated": "2012-09-19T23:59:26.159", "date_created": "2012-09-19T23:59:26.159", "identifier": "138386"}}, {"pk": 150, "model": "core.media", "fields": {"name": "Smashwords Version", "title": 742, "url": "", "deleted": false, "date_updated": "2012-09-19T23:59:26.159", "date_created": "2012-09-19T23:59:26.159", "identifier": "92529"}}, {"pk": 151, "model": "core.media", "fields": {"name": "Smashwords Version", "title": 723, "url": "", "deleted": false, "date_updated": "2012-09-19T23:59:26.159", "date_created": "2012-09-19T23:59:26.159", "identifier": "65510"}}, {"pk": 152, "model": "core.media", "fields": {"name": "Smashwords Version", "title": 748, "url": "", "deleted": false, "date_updated": "2012-09-19T23:59:26.159", "date_created": "2012-09-19T23:59:26.159", "identifier": "135491"}}, {"pk": 124, "model": "core.media", "fields": {"name": "Smashwords Version", "title": 675, "url": "", "deleted": false, "date_updated": "2012-09-19T23:59:26.159", "date_created": "2012-09-19T23:59:26.159", "identifier": "20839"}}, {"pk": 1, "model": "core.media", "fields": {"name": "Smashwords Version", "title": 360, "url": "", "deleted": false, "date_updated": "2012-09-19T23:59:26.159", "date_created": "2012-09-19T23:59:26.159", "identifier": "2966"}}, {"pk": 2, "model": "core.media", "fields": {"name": "Smashwords Version", "title": 257, "url": "", "deleted": false, "date_updated": "2012-09-19T23:59:26.159", "date_created": "2012-09-19T23:59:26.159", "identifier": "1657"}}, {"pk": 3, "model": "core.media", "fields": {"name": "Smashwords Version", "title": 406, "url": "", "deleted": false, "date_updated": "2012-09-19T23:59:26.159", "date_created": "2012-09-19T23:59:26.159", "identifier": "3182"}}, {"pk": 4, "model": "core.media", "fields": {"name": "Smashwords Version", "title": 409, "url": "", "deleted": false, "date_updated": "2012-09-19T23:59:26.159", "date_created": "2012-09-19T23:59:26.159", "identifier": "49221"}}, {"pk": 5, "model": "core.media", "fields": {"name": "Smashwords Version", "title": 388, "url": "", "deleted": false, "date_updated": "2012-09-19T23:59:26.159", "date_created": "2012-09-19T23:59:26.159", "identifier": "49221"}}, {"pk": 6, "model": "core.media", "fields": {"name": "Smashwords Version", "title": 347, "url": "", "deleted": false, "date_updated": "2012-09-19T23:59:26.159", "date_created": "2012-09-19T23:59:26.159", "identifier": "585"}}, {"pk": 7, "model": "core.media", "fields": {"name": "Smashwords Version", "title": 318, "url": "", "deleted": false, "date_updated": "2012-09-19T23:59:26.159", "date_created": "2012-09-19T23:59:26.159", "identifier": "942"}}, {"pk": 8, "model": "core.media", "fields": {"name": "Smashwords Version", "title": 285, "url": "", "deleted": false, "date_updated": "2012-09-19T23:59:26.159", "date_created": "2012-09-19T23:59:26.159", "identifier": "1022"}}, {"pk": 9, "model": "core.media", "fields": {"name": "Smashwords Version", "title": 346, "url": "", "deleted": false, "date_updated": "2012-09-19T23:59:26.159", "date_created": "2012-09-19T23:59:26.159", "identifier": "3289"}}, {"pk": 10, "model": "core.media", "fields": {"name": "Smashwords Version", "title": 394, "url": "", "deleted": false, "date_updated": "2012-09-19T23:59:26.159", "date_created": "2012-09-19T23:59:26.159", "identifier": "16142"}}, {"pk": 11, "model": "core.media", "fields": {"name": "Smashwords Version", "title": 413, "url": "", "deleted": false, "date_updated": "2012-09-19T23:59:26.159", "date_created": "2012-09-19T23:59:26.159", "identifier": "16145"}}, {"pk": 12, "model": "core.media", "fields": {"name": "Smashwords Version", "title": 325, "url": "", "deleted": false, "date_updated": "2012-09-19T23:59:26.159", "date_created": "2012-09-19T23:59:26.159", "identifier": "2008"}}, {"pk": 13, "model": "core.media", "fields": {"name": "Smashwords Version", "title": 380, "url": "", "deleted": false, "date_updated": "2012-09-19T23:59:26.159", "date_created": "2012-09-19T23:59:26.159", "identifier": "2022"}}, {"pk": 14, "model": "core.media", "fields": {"name": "Smashwords Version", "title": 417, "url": "", "deleted": false, "date_updated": "2012-09-19T23:59:26.159", "date_created": "2012-09-19T23:59:26.159", "identifier": "2006"}}, {"pk": 15, "model": "core.media", "fields": {"name": "Smashwords Version", "title": 307, "url": "", "deleted": false, "date_updated": "2012-09-19T23:59:26.159", "date_created": "2012-09-19T23:59:26.159", "identifier": "2020"}}, {"pk": 16, "model": "core.media", "fields": {"name": "Smashwords Version", "title": 240, "url": "", "deleted": false, "date_updated": "2012-09-19T23:59:26.159", "date_created": "2012-09-19T23:59:26.159", "identifier": "2019"}}, {"pk": 17, "model": "core.media", "fields": {"name": "Smashwords Version", "title": 205, "url": "", "deleted": false, "date_updated": "2012-09-19T23:59:26.159", "date_created": "2012-09-19T23:59:26.159", "identifier": "2006"}}, {"pk": 18, "model": "core.media", "fields": {"name": "Smashwords Version", "title": 286, "url": "", "deleted": false, "date_updated": "2012-09-19T23:59:26.159", "date_created": "2012-09-19T23:59:26.159", "identifier": "3039"}}, {"pk": 19, "model": "core.media", "fields": {"name": "Smashwords Version", "title": 419, "url": "", "deleted": false, "date_updated": "2012-09-19T23:59:26.159", "date_created": "2012-09-19T23:59:26.159", "identifier": "3399"}}, {"pk": 20, "model": "core.media", "fields": {"name": "Smashwords Version", "title": 354, "url": "", "deleted": false, "date_updated": "2012-09-19T23:59:26.159", "date_created": "2012-09-19T23:59:26.159", "identifier": "559"}}, {"pk": 21, "model": "core.media", "fields": {"name": "Smashwords Version", "title": 323, "url": "", "deleted": false, "date_updated": "2012-09-19T23:59:26.159", "date_created": "2012-09-19T23:59:26.159", "identifier": "558"}}, {"pk": 22, "model": "core.media", "fields": {"name": "Smashwords Version", "title": 261, "url": "", "deleted": false, "date_updated": "2012-09-19T23:59:26.159", "date_created": "2012-09-19T23:59:26.159", "identifier": "554"}}, {"pk": 23, "model": "core.media", "fields": {"name": "Smashwords Version", "title": 351, "url": "", "deleted": false, "date_updated": "2012-09-19T23:59:26.159", "date_created": "2012-09-19T23:59:26.159", "identifier": "3426"}}, {"pk": 24, "model": "core.media", "fields": {"name": "Smashwords Version", "title": 217, "url": "", "deleted": false, "date_updated": "2012-09-19T23:59:26.159", "date_created": "2012-09-19T23:59:26.159", "identifier": "3442"}}, {"pk": 25, "model": "core.media", "fields": {"name": "Smashwords Version", "title": 423, "url": "", "deleted": false, "date_updated": "2012-09-19T23:59:26.159", "date_created": "2012-09-19T23:59:26.159", "identifier": "16146"}}, {"pk": 26, "model": "core.media", "fields": {"name": "Smashwords Version", "title": 206, "url": "", "deleted": false, "date_updated": "2012-09-19T23:59:26.159", "date_created": "2012-09-19T23:59:26.159", "identifier": "2279"}}, {"pk": 27, "model": "core.media", "fields": {"name": "Smashwords Version", "title": 427, "url": "", "deleted": false, "date_updated": "2012-09-19T23:59:26.159", "date_created": "2012-09-19T23:59:26.159", "identifier": "49221"}}, {"pk": 28, "model": "core.media", "fields": {"name": "Smashwords Version", "title": 424, "url": "", "deleted": false, "date_updated": "2012-09-19T23:59:26.159", "date_created": "2012-09-19T23:59:26.159", "identifier": "3952"}}, {"pk": 29, "model": "core.media", "fields": {"name": "Smashwords Version", "title": 322, "url": "", "deleted": false, "date_updated": "2012-09-19T23:59:26.159", "date_created": "2012-09-19T23:59:26.159", "identifier": "3787"}}, {"pk": 30, "model": "core.media", "fields": {"name": "Smashwords Version", "title": 437, "url": "", "deleted": false, "date_updated": "2012-09-19T23:59:26.159", "date_created": "2012-09-19T23:59:26.159", "identifier": "4254"}}, {"pk": 31, "model": "core.media", "fields": {"name": "Smashwords Version", "title": 442, "url": "", "deleted": false, "date_updated": "2012-09-19T23:59:26.159", "date_created": "2012-09-19T23:59:26.159", "identifier": "69458"}}, {"pk": 32, "model": "core.media", "fields": {"name": "Smashwords Version", "title": 443, "url": "", "deleted": false, "date_updated": "2012-09-19T23:59:26.159", "date_created": "2012-09-19T23:59:26.159", "identifier": "4034"}}, {"pk": 33, "model": "core.media", "fields": {"name": "Smashwords Version", "title": 241, "url": "", "deleted": false, "date_updated": "2012-09-19T23:59:26.159", "date_created": "2012-09-19T23:59:26.159", "identifier": "5662"}}, {"pk": 34, "model": "core.media", "fields": {"name": "Smashwords Version", "title": 453, "url": "", "deleted": false, "date_updated": "2012-09-19T23:59:26.159", "date_created": "2012-09-19T23:59:26.159", "identifier": "4110"}}, {"pk": 35, "model": "core.media", "fields": {"name": "Smashwords Version", "title": 420, "url": "", "deleted": false, "date_updated": "2012-09-19T23:59:26.159", "date_created": "2012-09-19T23:59:26.159", "identifier": "6733"}}, {"pk": 36, "model": "core.media", "fields": {"name": "Smashwords Version", "title": 247, "url": "", "deleted": false, "date_updated": "2012-09-19T23:59:26.159", "date_created": "2012-09-19T23:59:26.159", "identifier": "6035"}}, {"pk": 37, "model": "core.media", "fields": {"name": "Smashwords Version", "title": 248, "url": "", "deleted": false, "date_updated": "2012-09-19T23:59:26.159", "date_created": "2012-09-19T23:59:26.159", "identifier": "6033"}}, {"pk": 38, "model": "core.media", "fields": {"name": "Smashwords Version", "title": 249, "url": "", "deleted": false, "date_updated": "2012-09-19T23:59:26.159", "date_created": "2012-09-19T23:59:26.159", "identifier": "6037"}}, {"pk": 39, "model": "core.media", "fields": {"name": "Smashwords Version", "title": 445, "url": "", "deleted": false, "date_updated": "2012-09-19T23:59:26.159", "date_created": "2012-09-19T23:59:26.159", "identifier": "6036"}}, {"pk": 40, "model": "core.media", "fields": {"name": "Smashwords Version", "title": 446, "url": "", "deleted": false, "date_updated": "2012-09-19T23:59:26.159", "date_created": "2012-09-19T23:59:26.159", "identifier": "6032"}}, {"pk": 41, "model": "core.media", "fields": {"name": "Smashwords Version", "title": 459, "url": "", "deleted": false, "date_updated": "2012-09-19T23:59:26.159", "date_created": "2012-09-19T23:59:26.159", "identifier": "6034"}}, {"pk": 42, "model": "core.media", "fields": {"name": "Smashwords Version", "title": 460, "url": "", "deleted": false, "date_updated": "2012-09-19T23:59:26.159", "date_created": "2012-09-19T23:59:26.159", "identifier": "6029"}}, {"pk": 43, "model": "core.media", "fields": {"name": "Smashwords Version", "title": 316, "url": "", "deleted": false, "date_updated": "2012-09-19T23:59:26.159", "date_created": "2012-09-19T23:59:26.159", "identifier": "7032"}}, {"pk": 44, "model": "core.media", "fields": {"name": "Smashwords Version", "title": 462, "url": "", "deleted": false, "date_updated": "2012-09-19T23:59:26.159", "date_created": "2012-09-19T23:59:26.159", "identifier": "7213"}}, {"pk": 45, "model": "core.media", "fields": {"name": "Smashwords Version", "title": 457, "url": "", "deleted": false, "date_updated": "2012-09-19T23:59:26.159", "date_created": "2012-09-19T23:59:26.159", "identifier": "4245"}}, {"pk": 46, "model": "core.media", "fields": {"name": "Smashwords Version", "title": 463, "url": "", "deleted": false, "date_updated": "2012-09-19T23:59:26.159", "date_created": "2012-09-19T23:59:26.159", "identifier": "5745"}}, {"pk": 47, "model": "core.media", "fields": {"name": "Smashwords Version", "title": 470, "url": "", "deleted": false, "date_updated": "2012-09-19T23:59:26.159", "date_created": "2012-09-19T23:59:26.159", "identifier": "6026"}}, {"pk": 48, "model": "core.media", "fields": {"name": "Smashwords Version", "title": 471, "url": "", "deleted": false, "date_updated": "2012-09-19T23:59:26.159", "date_created": "2012-09-19T23:59:26.159", "identifier": "7552"}}, {"pk": 49, "model": "core.media", "fields": {"name": "Smashwords Version", "title": 274, "url": "", "deleted": false, "date_updated": "2012-09-19T23:59:26.159", "date_created": "2012-09-19T23:59:26.159", "identifier": "8393"}}, {"pk": 51, "model": "core.media", "fields": {"name": "Smashwords Version", "title": 414, "url": "", "deleted": false, "date_updated": "2012-09-19T23:59:26.159", "date_created": "2012-09-19T23:59:26.159", "identifier": "9495"}}, {"pk": 52, "model": "core.media", "fields": {"name": "Smashwords Version", "title": 483, "url": "", "deleted": false, "date_updated": "2012-09-19T23:59:26.159", "date_created": "2012-09-19T23:59:26.159", "identifier": "9357"}}, {"pk": 53, "model": "core.media", "fields": {"name": "Smashwords Version", "title": 486, "url": "", "deleted": false, "date_updated": "2012-09-19T23:59:26.159", "date_created": "2012-09-19T23:59:26.159", "identifier": "8297"}}, {"pk": 54, "model": "core.media", "fields": {"name": "Smashwords Version", "title": 490, "url": "", "deleted": false, "date_updated": "2012-09-19T23:59:26.159", "date_created": "2012-09-19T23:59:26.159", "identifier": "6485"}}, {"pk": 55, "model": "core.media", "fields": {"name": "Smashwords Version", "title": 492, "url": "", "deleted": false, "date_updated": "2012-09-19T23:59:26.159", "date_created": "2012-09-19T23:59:26.159", "identifier": "10251"}}, {"pk": 56, "model": "core.media", "fields": {"name": "Smashwords Version", "title": 493, "url": "", "deleted": false, "date_updated": "2012-09-19T23:59:26.159", "date_created": "2012-09-19T23:59:26.159", "identifier": "10959"}}, {"pk": 57, "model": "core.media", "fields": {"name": "Smashwords Version", "title": 214, "url": "", "deleted": false, "date_updated": "2012-09-19T23:59:26.159", "date_created": "2012-09-19T23:59:26.159", "identifier": "8970"}}, {"pk": 58, "model": "core.media", "fields": {"name": "Smashwords Version", "title": 411, "url": "", "deleted": false, "date_updated": "2012-09-19T23:59:26.159", "date_created": "2012-09-19T23:59:26.159", "identifier": "7579"}}, {"pk": 59, "model": "core.media", "fields": {"name": "Smashwords Version", "title": 497, "url": "", "deleted": false, "date_updated": "2012-09-19T23:59:26.159", "date_created": "2012-09-19T23:59:26.159", "identifier": "11574"}}, {"pk": 60, "model": "core.media", "fields": {"name": "Smashwords Version", "title": 503, "url": "", "deleted": false, "date_updated": "2012-09-19T23:59:26.159", "date_created": "2012-09-19T23:59:26.159", "identifier": "12186"}}, {"pk": 61, "model": "core.media", "fields": {"name": "Smashwords Version", "title": 496, "url": "", "deleted": false, "date_updated": "2012-09-19T23:59:26.159", "date_created": "2012-09-19T23:59:26.159", "identifier": "13297"}}, {"pk": 62, "model": "core.media", "fields": {"name": "Smashwords Version", "title": 504, "url": "", "deleted": false, "date_updated": "2012-09-19T23:59:26.159", "date_created": "2012-09-19T23:59:26.159", "identifier": "6693"}}, {"pk": 63, "model": "core.media", "fields": {"name": "Smashwords Version", "title": 447, "url": "", "deleted": false, "date_updated": "2012-09-19T23:59:26.159", "date_created": "2012-09-19T23:59:26.159", "identifier": "14015"}}, {"pk": 64, "model": "core.media", "fields": {"name": "Smashwords Version", "title": 507, "url": "", "deleted": false, "date_updated": "2012-09-19T23:59:26.159", "date_created": "2012-09-19T23:59:26.159", "identifier": "10913"}}, {"pk": 65, "model": "core.media", "fields": {"name": "Smashwords Version", "title": 439, "url": "", "deleted": false, "date_updated": "2012-09-19T23:59:26.159", "date_created": "2012-09-19T23:59:26.159", "identifier": "14406"}}, {"pk": 66, "model": "core.media", "fields": {"name": "Smashwords Version", "title": 498, "url": "", "deleted": false, "date_updated": "2012-09-19T23:59:26.159", "date_created": "2012-09-19T23:59:26.159", "identifier": "15692"}}, {"pk": 67, "model": "core.media", "fields": {"name": "Smashwords Version", "title": 515, "url": "", "deleted": false, "date_updated": "2012-09-19T23:59:26.159", "date_created": "2012-09-19T23:59:26.159", "identifier": "903"}}, {"pk": 68, "model": "core.media", "fields": {"name": "Smashwords Version", "title": 456, "url": "", "deleted": false, "date_updated": "2012-09-19T23:59:26.159", "date_created": "2012-09-19T23:59:26.159", "identifier": "17277"}}, {"pk": 69, "model": "core.media", "fields": {"name": "Smashwords Version", "title": 524, "url": "", "deleted": false, "date_updated": "2012-09-19T23:59:26.159", "date_created": "2012-09-19T23:59:26.159", "identifier": "17426"}}, {"pk": 70, "model": "core.media", "fields": {"name": "Smashwords Version", "title": 532, "url": "", "deleted": false, "date_updated": "2012-09-19T23:59:26.159", "date_created": "2012-09-19T23:59:26.159", "identifier": "17896"}}, {"pk": 71, "model": "core.media", "fields": {"name": "Smashwords Version", "title": 535, "url": "", "deleted": false, "date_updated": "2012-09-19T23:59:26.159", "date_created": "2012-09-19T23:59:26.159", "identifier": "666"}}, {"pk": 72, "model": "core.media", "fields": {"name": "Smashwords Version", "title": 505, "url": "", "deleted": false, "date_updated": "2012-09-19T23:59:26.159", "date_created": "2012-09-19T23:59:26.159", "identifier": "7138"}}, {"pk": 73, "model": "core.media", "fields": {"name": "Smashwords Version", "title": 527, "url": "", "deleted": false, "date_updated": "2012-09-19T23:59:26.159", "date_created": "2012-09-19T23:59:26.159", "identifier": "13711"}}, {"pk": 74, "model": "core.media", "fields": {"name": "Smashwords Version", "title": 511, "url": "", "deleted": false, "date_updated": "2012-09-19T23:59:26.159", "date_created": "2012-09-19T23:59:26.159", "identifier": "6460"}}, {"pk": 75, "model": "core.media", "fields": {"name": "Smashwords Version", "title": 555, "url": "", "deleted": false, "date_updated": "2012-09-19T23:59:26.159", "date_created": "2012-09-19T23:59:26.159", "identifier": "18156"}}, {"pk": 76, "model": "core.media", "fields": {"name": "Smashwords Version", "title": 541, "url": "", "deleted": false, "date_updated": "2012-09-19T23:59:26.159", "date_created": "2012-09-19T23:59:26.159", "identifier": "19260"}}, {"pk": 77, "model": "core.media", "fields": {"name": "Smashwords Version", "title": 440, "url": "", "deleted": false, "date_updated": "2012-09-19T23:59:26.159", "date_created": "2012-09-19T23:59:26.159", "identifier": "27301"}}, {"pk": 78, "model": "core.media", "fields": {"name": "Smashwords Version", "title": 421, "url": "", "deleted": false, "date_updated": "2012-09-19T23:59:26.159", "date_created": "2012-09-19T23:59:26.159", "identifier": "25924"}}, {"pk": 79, "model": "core.media", "fields": {"name": "Smashwords Version", "title": 531, "url": "", "deleted": false, "date_updated": "2012-09-19T23:59:26.159", "date_created": "2012-09-19T23:59:26.159", "identifier": "15765"}}, {"pk": 80, "model": "core.media", "fields": {"name": "Smashwords Version", "title": 569, "url": "", "deleted": false, "date_updated": "2012-09-19T23:59:26.159", "date_created": "2012-09-19T23:59:26.159", "identifier": "21152"}}, {"pk": 81, "model": "core.media", "fields": {"name": "Smashwords Version", "title": 573, "url": "", "deleted": false, "date_updated": "2012-09-19T23:59:26.159", "date_created": "2012-09-19T23:59:26.159", "identifier": "10854"}}, {"pk": 82, "model": "core.media", "fields": {"name": "Smashwords Version", "title": 575, "url": "", "deleted": false, "date_updated": "2012-09-19T23:59:26.159", "date_created": "2012-09-19T23:59:26.159", "identifier": "49224"}}, {"pk": 83, "model": "core.media", "fields": {"name": "Smashwords Version", "title": 576, "url": "", "deleted": false, "date_updated": "2012-09-19T23:59:26.159", "date_created": "2012-09-19T23:59:26.159", "identifier": "26572"}}, {"pk": 84, "model": "core.media", "fields": {"name": "Smashwords Version", "title": 309, "url": "", "deleted": false, "date_updated": "2012-09-19T23:59:26.159", "date_created": "2012-09-19T23:59:26.159", "identifier": "34638"}}, {"pk": 85, "model": "core.media", "fields": {"name": "Smashwords Version", "title": 319, "url": "", "deleted": false, "date_updated": "2012-09-19T23:59:26.159", "date_created": "2012-09-19T23:59:26.159", "identifier": "45948"}}, {"pk": 86, "model": "core.media", "fields": {"name": "Smashwords Version", "title": 353, "url": "", "deleted": false, "date_updated": "2012-09-19T23:59:26.159", "date_created": "2012-09-19T23:59:26.159", "identifier": "46147"}}, {"pk": 87, "model": "core.media", "fields": {"name": "Smashwords Version", "title": 544, "url": "", "deleted": false, "date_updated": "2012-09-19T23:59:26.159", "date_created": "2012-09-19T23:59:26.159", "identifier": "23268"}}, {"pk": 88, "model": "core.media", "fields": {"name": "Smashwords Version", "title": 580, "url": "", "deleted": false, "date_updated": "2012-09-19T23:59:26.159", "date_created": "2012-09-19T23:59:26.159", "identifier": "28052"}}, {"pk": 89, "model": "core.media", "fields": {"name": "Smashwords Version", "title": 517, "url": "", "deleted": false, "date_updated": "2012-09-19T23:59:26.159", "date_created": "2012-09-19T23:59:26.159", "identifier": "32019"}}, {"pk": 90, "model": "core.media", "fields": {"name": "Smashwords Version", "title": 597, "url": "", "deleted": false, "date_updated": "2012-09-19T23:59:26.159", "date_created": "2012-09-19T23:59:26.159", "identifier": "25708"}}, {"pk": 91, "model": "core.media", "fields": {"name": "Smashwords Version", "title": 288, "url": "", "deleted": false, "date_updated": "2012-09-19T23:59:26.159", "date_created": "2012-09-19T23:59:26.159", "identifier": "41652"}}, {"pk": 92, "model": "core.media", "fields": {"name": "Smashwords Version", "title": 604, "url": "", "deleted": false, "date_updated": "2012-09-19T23:59:26.159", "date_created": "2012-09-19T23:59:26.159", "identifier": "49224"}}, {"pk": 93, "model": "core.media", "fields": {"name": "Smashwords Version", "title": 607, "url": "", "deleted": false, "date_updated": "2012-09-19T23:59:26.159", "date_created": "2012-09-19T23:59:26.159", "identifier": "37162"}}, {"pk": 94, "model": "core.media", "fields": {"name": "Smashwords Version", "title": 608, "url": "", "deleted": false, "date_updated": "2012-09-19T23:59:26.159", "date_created": "2012-09-19T23:59:26.159", "identifier": "46578"}}, {"pk": 95, "model": "core.media", "fields": {"name": "Smashwords Version", "title": 613, "url": "", "deleted": false, "date_updated": "2012-09-19T23:59:26.159", "date_created": "2012-09-19T23:59:26.159", "identifier": "32239"}}, {"pk": 96, "model": "core.media", "fields": {"name": "Smashwords Version", "title": 615, "url": "", "deleted": false, "date_updated": "2012-09-19T23:59:26.159", "date_created": "2012-09-19T23:59:26.159", "identifier": "38666"}}, {"pk": 97, "model": "core.media", "fields": {"name": "Smashwords Version", "title": 611, "url": "", "deleted": false, "date_updated": "2012-09-19T23:59:26.159", "date_created": "2012-09-19T23:59:26.159", "identifier": "47944"}}, {"pk": 98, "model": "core.media", "fields": {"name": "Smashwords Version", "title": 603, "url": "", "deleted": false, "date_updated": "2012-09-19T23:59:26.159", "date_created": "2012-09-19T23:59:26.159", "identifier": "34925"}}, {"pk": 99, "model": "core.media", "fields": {"name": "Smashwords Version", "title": 619, "url": "", "deleted": false, "date_updated": "2012-09-19T23:59:26.159", "date_created": "2012-09-19T23:59:26.159", "identifier": "6584"}}, {"pk": 100, "model": "core.media", "fields": {"name": "Smashwords Version", "title": 130, "url": "", "deleted": false, "date_updated": "2012-09-19T23:59:26.159", "date_created": "2012-09-19T23:59:26.159", "identifier": "14108"}}, {"pk": 101, "model": "core.media", "fields": {"name": "Smashwords Version", "title": 630, "url": "", "deleted": false, "date_updated": "2012-09-19T23:59:26.159", "date_created": "2012-09-19T23:59:26.159", "identifier": "49224"}}, {"pk": 102, "model": "core.media", "fields": {"name": "Smashwords Version", "title": 267, "url": "", "deleted": false, "date_updated": "2012-09-19T23:59:26.159", "date_created": "2012-09-19T23:59:26.159", "identifier": "45135"}}, {"pk": 103, "model": "core.media", "fields": {"name": "Smashwords Version", "title": 502, "url": "", "deleted": false, "date_updated": "2012-09-19T23:59:26.159", "date_created": "2012-09-19T23:59:26.159", "identifier": "9238"}}, {"pk": 104, "model": "core.media", "fields": {"name": "Smashwords Version", "title": 629, "url": "", "deleted": false, "date_updated": "2012-09-19T23:59:26.159", "date_created": "2012-09-19T23:59:26.159", "identifier": "24640"}}, {"pk": 105, "model": "core.media", "fields": {"name": "Smashwords Version", "title": 74, "url": "", "deleted": false, "date_updated": "2012-09-19T23:59:26.159", "date_created": "2012-09-19T23:59:26.159", "identifier": "2064"}}, {"pk": 106, "model": "core.media", "fields": {"name": "Smashwords Version", "title": 84, "url": "", "deleted": false, "date_updated": "2012-09-19T23:59:26.159", "date_created": "2012-09-19T23:59:26.159", "identifier": "15053"}}, {"pk": 107, "model": "core.media", "fields": {"name": "Smashwords Version", "title": 634, "url": "", "deleted": false, "date_updated": "2012-09-19T23:59:26.159", "date_created": "2012-09-19T23:59:26.159", "identifier": "37088"}}, {"pk": 108, "model": "core.media", "fields": {"name": "Smashwords Version", "title": 66, "url": "", "deleted": false, "date_updated": "2012-09-19T23:59:26.159", "date_created": "2012-09-19T23:59:26.159", "identifier": "54751"}}, {"pk": 109, "model": "core.media", "fields": {"name": "Smashwords Version", "title": 518, "url": "", "deleted": false, "date_updated": "2012-09-19T23:59:26.159", "date_created": "2012-09-19T23:59:26.159", "identifier": "62085"}}, {"pk": 110, "model": "core.media", "fields": {"name": "Smashwords Version", "title": 509, "url": "", "deleted": false, "date_updated": "2012-09-19T23:59:26.159", "date_created": "2012-09-19T23:59:26.159", "identifier": "66250"}}, {"pk": 111, "model": "core.media", "fields": {"name": "Smashwords Version", "title": 648, "url": "", "deleted": false, "date_updated": "2012-09-19T23:59:26.159", "date_created": "2012-09-19T23:59:26.159", "identifier": "45842"}}, {"pk": 112, "model": "core.media", "fields": {"name": "Smashwords Version", "title": 652, "url": "", "deleted": false, "date_updated": "2012-09-19T23:59:26.159", "date_created": "2012-09-19T23:59:26.159", "identifier": "67979"}}, {"pk": 113, "model": "core.media", "fields": {"name": "Smashwords Version", "title": 95, "url": "", "deleted": false, "date_updated": "2012-09-19T23:59:26.159", "date_created": "2012-09-19T23:59:26.159", "identifier": "59912"}}, {"pk": 114, "model": "core.media", "fields": {"name": "Smashwords Version", "title": 287, "url": "", "deleted": false, "date_updated": "2012-09-19T23:59:26.159", "date_created": "2012-09-19T23:59:26.159", "identifier": "62901"}}, {"pk": 115, "model": "core.media", "fields": {"name": "Smashwords Version", "title": 135, "url": "", "deleted": false, "date_updated": "2012-09-19T23:59:26.159", "date_created": "2012-09-19T23:59:26.159", "identifier": "62901"}}, {"pk": 116, "model": "core.media", "fields": {"name": "Smashwords Version", "title": 211, "url": "", "deleted": false, "date_updated": "2012-09-19T23:59:26.159", "date_created": "2012-09-19T23:59:26.159", "identifier": "62901"}}]